petab_gui/C.py
petab_gui/__init__.py
petab_gui/__main__.py
petab_gui/app.py
petab_gui/commands.py
petab_gui/settings_manager.py
petab_gui/stylesheet.css
petab_gui/utils.py
petab_gui/assets/PEtab.png
petab_gui/controllers/__init__.py
petab_gui/controllers/default_handler.py
petab_gui/controllers/logger_controller.py
petab_gui/controllers/mother_controller.py
petab_gui/controllers/sbml_controller.py
petab_gui/controllers/table_controllers.py
petab_gui/controllers/utils.py
petab_gui/example/__init__.py
petab_gui/example/Boehm/cond.tsv
petab_gui/example/Boehm/meas.tsv
petab_gui/example/Boehm/obs.tsv
petab_gui/example/Boehm/para.tsv
petab_gui/example/Boehm/problem.yaml
petab_gui/example/Boehm/sbml_model.xml
petab_gui/example/Simple_Conversion/conditions.tsv
petab_gui/example/Simple_Conversion/measurements.tsv
petab_gui/example/Simple_Conversion/model.xml
petab_gui/example/Simple_Conversion/observables.tsv
petab_gui/example/Simple_Conversion/parameters.tsv
petab_gui/example/Simple_Conversion/problem.yaml
petab_gui/models/__init__.py
petab_gui/models/pandas_table_model.py
petab_gui/models/petab_model.py
petab_gui/models/sbml_model.py
petab_gui/models/tooltips.py
petab_gui/views/__init__.py
petab_gui/views/context_menu_mananger.py
petab_gui/views/find_replace_bar.py
petab_gui/views/logger.py
petab_gui/views/main_view.py
petab_gui/views/other_views.py
petab_gui/views/sbml_view.py
petab_gui/views/simple_plot_view.py
petab_gui/views/table_view.py
petab_gui/views/task_bar.py
petab_gui/views/utils.py
petab_gui/views/whats_this.py
petab_gui-0.2.0.dist-info/licenses/LICENSE
petab_gui-0.2.0.dist-info/METADATA
petab_gui-0.2.0.dist-info/WHEEL
petab_gui-0.2.0.dist-info/entry_points.txt
petab_gui-0.2.0.dist-info/top_level.txt
petab_gui-0.2.0.dist-info/RECORD
