Metadata-Version: 2.4
Name: PEtab-GUI
Version: 0.2.0
Summary: Graphical user interface for the PEtab format
Author-email: Paul Jonas Jost <jost.pauljonas@gmail.com>, "Frank T. Bergmann" <frank.thomas.bergmann@gmail.com>
Maintainer-email: Paul Jonas Jost <jost.pauljonas@gmail.com>, "Frank T. Bergmann" <frank.thomas.bergmann@gmail.com>
Project-URL: Repository, https://github.com/PEtab-dev/PEtabGUI
Project-URL: Issues, https://github.com/PEtab-dev/PEtabGUI/issues
Requires-Python: >=3.11
License-File: LICENSE
Requires-Dist: pyside6
Requires-Dist: pandas
Requires-Dist: antimony
Requires-Dist: python-libsbml
Requires-Dist: matplotlib
Requires-Dist: petab[combine]>=0.6.0
Requires-Dist: qtawesome
Requires-Dist: copasi-basico
Requires-Dist: copasi-petab-importer
Requires-Dist: pyobjc; sys_platform == "darwin"
Provides-Extra: doc
Requires-Dist: sphinx; extra == "doc"
Requires-Dist: sphinx-rtd-theme; extra == "doc"
Requires-Dist: myst-parser; extra == "doc"
Requires-Dist: sphinx_copybutton; extra == "doc"
Requires-Dist: sphinx-design; extra == "doc"
Dynamic: license-file
